{
  "torneios": [
    {
      "etapaId": "e001",
      "estado": "grupos",
      "numGrupos": 5,
      "cabecasDeSerie": [
        "jmntii5ehdkwg",
        "j001",
        "j006",
        "jmntihrfco8zm",
        "jmntir2jlvvot"
      ],
      "grupos": [
        {
          "id": "g1",
          "campo": 1,
          "jogadores": [
            "j006",
            "jmntiqp3bcz0c",
            "jmnulp1rji487"
          ],
          "jogos": [],
          "classificacao": [],
          "classificacaoEditada": false
        },
        {
          "id": "g2",
          "campo": 2,
          "jogadores": [
            "j001",
            "jmntipl8cugw0",
            "j005"
          ],
          "jogos": [],
          "classificacao": [],
          "classificacaoEditada": false
        },
        {
          "id": "g3",
          "campo": 3,
          "jogadores": [
            "jmntihrfco8zm",
            "j003",
            "j002"
          ],
          "jogos": [],
          "classificacao": [],
          "classificacaoEditada": false
        },
        {
          "id": "g4",
          "campo": 4,
          "jogadores": [
            "jmntir2jlvvot",
            "jmntiou1qw765",
            "j004"
          ],
          "jogos": [],
          "classificacao": [],
          "classificacaoEditada": false
        },
        {
          "id": "g5",
          "campo": 5,
          "jogadores": [
            "jmntii5ehdkwg",
            "jmntiomivpeaw",
            "jmntipxsi5f0s"
          ],
          "jogos": [],
          "classificacao": [],
          "classificacaoEditada": false
        }
      ],
      "quadroPrincipal": {
        "posicoes": [],
        "rondas": []
      },
      "quadroB": {
        "posicoes": [],
        "rondas": []
      },
      "classificacaoFinal": []
    }
  ]
}